{"0":"light display","1":"speaker (uncertain)","10":"speaker","11":"speaker","12":"cushion (uncertain)","13":"person","14":"speaker","15":"speaker","16":"banner","17":"speaker","18":"tablecloth","19":"cell phone","2":"person","20":"person","21":"television screen (uncertain)","22":"speaker (uncertain)","23":"speaker","24":"speaker","25":"screen","26":"light source (uncertain)","27":"person","28":"pole","29":"chair (uncertain)","3":"person","30":"screen","31":"chair (uncertain)","32":"handle (uncertain)","33":"speaker (uncertain)","34":"speaker","35":"stage structure","36":"person","37":"speaker (uncertain)","38":"person","4":"person","5":"sneakers","6":"arm (uncertain)","7":"cell phone","8":"stage light (uncertain)","9":"object (uncertain)","-1":"camera"}