{"1":"person","10":"pole","11":"rearview mirror","12":"shirt","13":"jacket","14":"trash can (uncertain)","15":"building","16":"signboard","19":"signboard","20":"jeans (uncertain)","21":"fender (uncertain)","22":"calendar page","23":"headscarf","24":"garment (uncertain)","25":"box","26":"dress","27":"tablecloth (uncertain)","28":"shawl","29":"bamboo stalk","30":"wall","31":"vehicle (uncertain)","32":"telephone pole","33":"person (uncertain)","35":"awning","36":"signboard","38":"truck","39":"minivan","40":"person","41":"billboard","45":"person","46":"auto rickshaw","48":"signboard","49":"poster","5":"pillar","55":"person","56":"box (uncertain)","6":"umbrella","7":"skirt","8":"building","9":"bus","-1":"camera"}