{"1":"cat","11":"cat","13":"cat","14":"door frame (uncertain)","15":"bath mat","16":"floor","2":"sleeve (uncertain)","21":"cat","22":"cat","23":"door (uncertain)","25":"cabinet","32":"curtain","33":"cat tunnel","35":"vase (uncertain)","37":"door (uncertain)","39":"jacket","42":"cat","43":"door frame (uncertain)","44":"door frame (uncertain)","45":"basket","48":"cat","50":"door","52":"cabinet","54":"doormat","56":"cabinet","57":"table","59":"place mat","60":"table","64":"window","68":"faucet","71":"window (uncertain)","72":"wall","73":"napkin","77":"sleeve","8":"cat","80":"door frame (uncertain)","82":"cat","83":"wall","88":"wall","89":"cat statue","-1":"camera"}