{"0":"dog","1":"cabinet","10":"object (uncertain)","11":"tile (uncertain)","12":"mirror","13":"table","14":"door frame (uncertain)","15":"ladder","16":"curtain","17":"curtain","18":"object (uncertain)","19":"stool","2":"drawer (uncertain)","20":"pole","21":"object (uncertain)","22":"pipe (uncertain)","23":"wheel (uncertain)","24":"wall","25":"bowl (uncertain)","26":"spray bottle (uncertain)","27":"bottle","28":"bathtub (uncertain)","29":"broom handle","3":"cabinet (uncertain)","30":"shoe (uncertain)","31":"bowl","32":"bucket (uncertain)","4":"curtain","5":"towel","6":"curtain (uncertain)","7":"flowerpot (uncertain)","8":"object","9":"vent (uncertain)","-1":"camera"}