{"0":"person (uncertain)","1":"fedora","11":"poster","12":"floor","13":"object (uncertain)","14":"person","15":"street light (uncertain)","16":"signboard","17":"signboard","2":"sneakers","21":"counter","23":"column","24":"lantern","25":"trousers","26":"refrigerator","29":"person","3":"trousers (uncertain)","30":"person (uncertain)","31":"person","32":"structure (uncertain)","33":"pole","34":"person","35":"structure","36":"panel","37":"television","38":"pole (uncertain)","39":"window","4":"shoe","40":"refrigerator","41":"structure","43":"coat","44":"object (uncertain)","45":"poster","46":"plastic bag (uncertain)","47":"signboard","5":"ticket machine","6":"television","7":"signboard (uncertain)","8":"ceiling tile","9":"person (uncertain)","-1":"camera"}