{"0":"person (uncertain)","1":"person","10":"person","11":"person","12":"person","13":"person","14":"person","15":"person","16":"person","17":"person","18":"bottle","19":"ceiling light fixture","2":"bottle","20":"headscarf","21":"wall or panel (uncertain)","22":"tablecloth","23":"curtain","24":"light fixture (uncertain)","25":"person","26":"chair","27":"object (uncertain)","28":"hand","3":"handbag","33":"chair","34":"person","36":"ceiling fan","37":"person","38":"ceiling fan","4":"blouse","41":"dress","44":"hairstyle","45":"cell phone (uncertain)","46":"person","47":"person (uncertain)","48":"person","49":"fabric (uncertain)","5":"person","7":"braid (uncertain)","8":"person","9":"curtain","-1":"camera"}