{"0":"person","1":"person","102":"shopping cart","103":"signboard","104":"tray","107":"signboard","108":"pendant lamp","109":"chair","113":"handcart","114":"tabletop","118":"chair","119":"object (uncertain)","120":"chair","123":"box","125":"chair","140":"poster","142":"wall panel (uncertain)","143":"signboard","144":"wall panel","17":"ceiling","18":"object (uncertain)","19":"shirt","2":"person","32":"garment","33":"crate","4":"handbag","43":"person","44":"jeans (uncertain)","48":"table","49":"wall panel","52":"shopping cart","6":"label (uncertain)","63":"ceiling light fixture","68":"grille (uncertain)","83":"box","87":"person","88":"rug","91":"tablecloth","96":"signboard","98":"display case","-1":"camera"}