{"0":"person","1":"person (uncertain)","10":"ceiling","11":"pole","12":"stool","13":"book (uncertain)","14":"bowl","15":"chair leg (uncertain)","16":"lightbulb","17":"paper (uncertain)","18":"wall","19":"poster","2":"shirt","20":"pipe","21":"cabinet","22":"person","23":"lamp shade (uncertain)","24":"stool","25":"poster","26":"fluorescent light fixture (uncertain)","27":"table leg (uncertain)","3":"person","4":"desk","5":"chair","6":"light source","7":"desk","8":"papers","9":"chair","-1":"camera"}